timeoutcall/__init__.py
timeoutcall/test.py
timeoutcall/testcall.py
timeoutcall-1.0.dist-info/LICENSE
timeoutcall-1.0.dist-info/METADATA
timeoutcall-1.0.dist-info/WHEEL
timeoutcall-1.0.dist-info/top_level.txt
timeoutcall-1.0.dist-info/RECORD
