Metadata-Version: 2.1
Name: timeoutcall
Version: 1.0
Summary: A package designed to kill a function after a specified amount of time.
Home-page: https://github.com/xyzpw/timeoutcall/
Author: xyzpw
Maintainer: xyzpw
License: MIT
Keywords: timeout,sleep,wait,decorator
Classifier: Programming Language :: Python :: 3
Classifier: Programming Language :: Python :: 3.8
Classifier: Programming Language :: Python :: 3.9
Classifier: Programming Language :: Python :: 3.10
Classifier: Programming Language :: Python :: 3.11
Classifier: License :: OSI Approved :: MIT License
Classifier: Operating System :: POSIX :: Linux
Classifier: Intended Audience :: Developers
Requires-Python: >=3.8
License-File: LICENSE
